src/__init__.py
src/cli.py
src/crypto.py
src/key_manager.py
src/utils.py
devdotenv-1.0.1.dist-info/METADATA
devdotenv-1.0.1.dist-info/WHEEL
devdotenv-1.0.1.dist-info/entry_points.txt
devdotenv-1.0.1.dist-info/licenses/LICENSE
devdotenv-1.0.1.dist-info/RECORD
