Metadata-Version: 2.4
Name: devdotenv
Version: 1.0.1
Summary: A CLI tool for securely encrypting and decrypting .env files using AES-256-GCM
Project-URL: Homepage, https://github.com/guinat/devdotenv-python
Project-URL: Repository, https://github.com/guinat/devdotenv-python
Project-URL: Documentation, https://github.com/guinat/devdotenv-python#readme
Project-URL: Bug Reports, https://github.com/guinat/devdotenv-python/issues
Author-email: guinat <guihotnathan@gmail.com>
License: MIT
License-File: LICENSE
Keywords: aes,cli,dotenv,encryption,env,environment,security,variables
Classifier: Development Status :: 5 - Production/Stable
Classifier: Intended Audience :: Developers
Classifier: License :: OSI Approved :: MIT License
Classifier: Operating System :: OS Independent
Classifier: Programming Language :: Python :: 3
Classifier: Programming Language :: Python :: 3.8
Classifier: Programming Language :: Python :: 3.9
Classifier: Programming Language :: Python :: 3.10
Classifier: Programming Language :: Python :: 3.11
Classifier: Programming Language :: Python :: 3.12
Classifier: Topic :: Security :: Cryptography
Classifier: Topic :: Software Development :: Libraries :: Python Modules
Classifier: Topic :: System :: Systems Administration
Requires-Python: >=3.8.1
Requires-Dist: click>=8.0.0
Requires-Dist: colorama>=0.4.6
Requires-Dist: cryptography>=41.0.0
Provides-Extra: dev
Requires-Dist: black>=23.0.0; extra == 'dev'
Requires-Dist: flake8>=6.0.0; extra == 'dev'
Requires-Dist: isort>=5.12.0; extra == 'dev'
Requires-Dist: mypy>=1.0.0; extra == 'dev'
Requires-Dist: pytest-cov>=4.0.0; extra == 'dev'
Requires-Dist: pytest>=7.0.0; extra == 'dev'
